quick_click_auto/__init__.py
quick_click_auto/constants.py
quick_click_auto/core.py
quick_click_auto/exceptions.py
quick_click_auto/py.typed
quick_click_auto/utils.py
quick_click_auto-1.0.5.dist-info/LICENSE
quick_click_auto-1.0.5.dist-info/METADATA
quick_click_auto-1.0.5.dist-info/WHEEL
quick_click_auto-1.0.5.dist-info/RECORD
