Metadata-Version: 2.3
Name: quick-click-auto
Version: 1.0.5
Summary:  Enable quick tab autocompletion for complex Click CLI applications. 
License: MIT
Keywords: click,autocomplete,shell
Author: Nim
Author-email: nim@systemli.org
Maintainer: Nim
Maintainer-email: nim@systemli.org
Requires-Python: >=3.7,<4.0
Classifier: License :: OSI Approved :: MIT License
Classifier: Natural Language :: English
Classifier: Operating System :: OS Independent
Classifier: Programming Language :: Python
Classifier: Programming Language :: Python :: 3
Classifier: Programming Language :: Python :: 3.7
Classifier: Programming Language :: Python :: 3.8
Classifier: Programming Language :: Python :: 3.9
Classifier: Programming Language :: Python :: 3.10
Classifier: Programming Language :: Python :: 3.11
Classifier: Programming Language :: Python :: 3.12
Classifier: Programming Language :: Python :: 3.13
Classifier: Programming Language :: Python :: Implementation :: PyPy
Classifier: Topic :: Software Development
Requires-Dist: click (>=8.1.4,<9.0.0)
Project-URL: Documentation, https://github.com/nimrod-a/quick-click-auto/blob/main/README.md
Project-URL: Homepage, https://github.com/nimrod-a/quick-click-auto
Project-URL: Repository, https://github.com/nimrod-a/quick-click-auto
